[
    {
        "companyInfo": {
            "companyID": "999",
            "counterNumber": 1,
            "division": "888",
            "warehouse": "US01"
        },
        "messageInfo": {
            "loginAttemptMsg": "",
            "loginAttemptStatus": "",
            "numberOfRecords": "20",
            "processMsg": "Displaying 20 records. Please narrow down search...",
            "statusCode": "0",
            "statusMsg": "Success"
        },
        "productInfo": [
            {
                "HSNCode": "62034100",
                "UOM": "PCS",
                "aliasNumber": "",
                "balance": 94,
                "imageFileName": "http://172.24.1.56:7002/ETPStoreServiceV5.5/ProductImageDownloadServlet?imagename=044APMWWPANTS-001-00001.jpg",
                "itemDescription": "Black Large",
                "itemName": "ALLEN SOLLY MEN PANTS INTEGRAT",
                "itemNumber": "044APMWWPANTS-001-00001",
                "location": "APP01",
                "productGroup": "MN-WW",
                "salesPrice": 60000
            },
            {
                "HSNCode": "68129100",
                "UOM": "PCS",
                "aliasNumber": "",
                "balance": 172,
                "imageFileName": "http://172.24.1.56:7002/ETPStoreServiceV5.5/ProductImageDownloadServlet?imagename=044APMWWPANTS-001-00004.jpg",
                "itemDescription": "White Large",
                "itemName": "ALLEN SOLLY MEN PANTS INTEGRAT",
                "itemNumber": "044APMWWPANTS-001-00004",
                "location": "APP01",
                "productGroup": "MN-WW",
                "salesPrice": 50
            },
            {
                "HSNCode": "68129100",
                "UOM": "PCS",
                "aliasNumber": "",
                "balance": 144,
                "imageFileName": "http://172.24.1.56:7002/ETPStoreServiceV5.5/ProductImageDownloadServlet?imagename=055APWWWJEANS-001-00001.jpg",
                "itemDescription": "Aqua Medium",
                "itemName": "CALVIN KLIEN WOMEN JEANS INTG ",
                "itemNumber": "055APWWWJEANS-001-00001",
                "location": "APP01",
                "productGroup": "WN-WW",
                "salesPrice": 7
            },
            {
                "HSNCode": "62034100",
                "UOM": "PCS",
                "aliasNumber": "",
                "balance": 1,
                "imageFileName": "http://172.24.1.56:7002/ETPStoreServiceV5.5/ProductImageDownloadServlet?imagename=055APWWWJEANS-001-00003.jpg",
                "itemDescription": "Blue Violet Medium",
                "itemName": "CALVIN KLIEN WOMEN JEANS INTG ",
                "itemNumber": "055APWWWJEANS-001-00003",
                "location": "APP01",
                "productGroup": "WN-WW",
                "salesPrice": 250
            },
            {
                "HSNCode": "62034100",
                "UOM": "PCS",
                "aliasNumber": "",
                "balance": 856,
                "imageFileName": "http://172.24.1.56:7002/ETPStoreServiceV5.5/ProductImageDownloadServlet?imagename=055APWWWJEANS-001-00003.jpg",
                "itemDescription": "Blue Violet Medium",
                "itemName": "CALVIN KLIEN WOMEN JEANS INTG ",
                "itemNumber": "055APWWWJEANS-001-00003",
                "location": "APP01",
                "productGroup": "WN-WW",
                "salesPrice": 250
            },
            {
                "HSNCode": "62034100",
                "UOM": "PCS",
                "aliasNumber": "",
                "balance": 933,
                "imageFileName": "http://172.24.1.56:7002/ETPStoreServiceV5.5/ProductImageDownloadServlet?imagename=106APMWWTROUS-001-00001.jpg",
                "itemDescription": "PURPLE Medium",
                "itemName": "LOUIS PHILLIPE TROUSER MENT IN",
                "itemNumber": "106APMWWTROUS-001-00001",
                "location": "APP01",
                "productGroup": "MN-WW",
                "salesPrice": 1000
            },
            {
                "HSNCode": "62034100",
                "UOM": "PCS",
                "aliasNumber": "",
                "balance": 1000,
                "imageFileName": "http://172.24.1.56:7002/ETPStoreServiceV5.5/ProductImageDownloadServlet?imagename=106APMWWTROUS-001-00001.jpg",
                "itemDescription": "PURPLE Medium",
                "itemName": "LOUIS PHILLIPE TROUSER MENT IN",
                "itemNumber": "106APMWWTROUS-001-00001",
                "location": "APP01",
                "productGroup": "MN-WW",
                "salesPrice": 1000
            },
            {
                "HSNCode": "12345648",
                "UOM": "PCS",
                "aliasNumber": "",
                "balance": 969,
                "imageFileName": "http://172.24.1.56:7002/ETPStoreServiceV5.5/ProductImageDownloadServlet?imagename=106APMWWTROUS-001-00002.jpg",
                "itemDescription": "Black Medium",
                "itemName": "LOUIS PHILLIPE TROUSER MENT IN",
                "itemNumber": "106APMWWTROUS-001-00002",
                "location": "APP01",
                "productGroup": "MN-WW",
                "salesPrice": 50000
            },
            {
                "HSNCode": "",
                "UOM": "PCS",
                "aliasNumber": "",
                "balance": 1000,
                "imageFileName": "http://172.24.1.56:7002/ETPStoreServiceV5.5/ProductImageDownloadServlet?imagename=106APMWWTROUS-001-00003.jpg",
                "itemDescription": "Pink Medium",
                "itemName": "LOUIS PHILLIPE TROUSER MENT IN",
                "itemNumber": "106APMWWTROUS-001-00003",
                "location": "APP01",
                "productGroup": "MN-WW",
                "salesPrice": 200
            },
            {
                "HSNCode": "",
                "UOM": "PCS",
                "aliasNumber": "",
                "balance": 1000,
                "imageFileName": "http://172.24.1.56:7002/ETPStoreServiceV5.5/ProductImageDownloadServlet?imagename=106APMWWTROUS-001-00004.jpg",
                "itemDescription": "BEIGE Medium",
                "itemName": "LOUIS PHILLIPE TROUSER MENT IN",
                "itemNumber": "106APMWWTROUS-001-00004",
                "location": "APP01",
                "productGroup": "MN-WW",
                "salesPrice": 44
            },
            {
                "HSNCode": "62034100",
                "UOM": "PCS",
                "aliasNumber": "",
                "balance": 775,
                "imageFileName": "http://172.24.1.56:7002/ETPStoreServiceV5.5/ProductImageDownloadServlet?imagename=ACKIDBANGMETFOSSIL-1-00001.jpg",
                "itemDescription": "Black Medium",
                "itemName": "Kids Metal Bangle Black Medium",
                "itemNumber": "ACKIDBANGMETFOSSIL-1-00001",
                "location": "APP01",
                "productGroup": "BANGL",
                "salesPrice": 200
            },
            {
                "HSNCode": "62034100",
                "UOM": "PCS",
                "aliasNumber": "",
                "balance": 881,
                "imageFileName": "http://172.24.1.56:7002/ETPStoreServiceV5.5/ProductImageDownloadServlet?imagename=ACKIDBANGMETFOSSIL-1-00002.jpg",
                "itemDescription": "MAGENTA Small",
                "itemName": "Kids Metal Bangle MAGENTA Smal",
                "itemNumber": "ACKIDBANGMETFOSSIL-1-00002",
                "location": "APP01",
                "productGroup": "BANGL",
                "salesPrice": 300
            },
            {
                "HSNCode": "62034100",
                "UOM": "PCS",
                "aliasNumber": "",
                "balance": 970,
                "imageFileName": "http://172.24.1.56:7002/ETPStoreServiceV5.5/ProductImageDownloadServlet?imagename=ACKIDBANGMETFOSSIL-1-00003.jpg",
                "itemDescription": "MAGENTA Xtra Large",
                "itemName": "أطفال معدن سوار أرجواني إكسترا",
                "itemNumber": "ACKIDBANGMETFOSSIL-1-00003",
                "location": "APP01",
                "productGroup": "BANGL",
                "salesPrice": 7
            },
            {
                "HSNCode": "62034100",
                "UOM": "PCS",
                "aliasNumber": "",
                "balance": 902,
                "imageFileName": "http://172.24.1.56:7002/ETPStoreServiceV5.5/ProductImageDownloadServlet?imagename=ACKIDBANGMETFOSSIL-1-00004.jpg",
                "itemDescription": "Black Small",
                "itemName": "Kids Metal Bangle Black Small",
                "itemNumber": "ACKIDBANGMETFOSSIL-1-00004",
                "location": "APP01",
                "productGroup": "BANGL",
                "salesPrice": 250
            },
            {
                "HSNCode": "62034100",
                "UOM": "PCS",
                "aliasNumber": "",
                "balance": 910,
                "imageFileName": "http://172.24.1.56:7002/ETPStoreServiceV5.5/ProductImageDownloadServlet?imagename=ACKIDBANGMETFOSSIL-1-00005.jpg",
                "itemDescription": "SILVER 4XL",
                "itemName": "Kids Metal Bangle SILVER 4XL",
                "itemNumber": "ACKIDBANGMETFOSSIL-1-00005",
                "location": "APP01",
                "productGroup": "BANGL",
                "salesPrice": 200
            },
            {
                "HSNCode": "",
                "UOM": "PCS",
                "aliasNumber": "",
                "balance": 1000,
                "imageFileName": "http://172.24.1.56:7002/ETPStoreServiceV5.5/ProductImageDownloadServlet?imagename=ACKIDBELTJEBURTON-1.jpg",
                "itemDescription": "Kids Belts Madison Metal Tip Belt",
                "itemName": "Kids MMT Belt",
                "itemNumber": "ACKIDBELTJEBURTON-1",
                "location": "APP01",
                "productGroup": "BELTS",
                "salesPrice": 4
            },
            {
                "HSNCode": "61012000",
                "UOM": "PCS",
                "aliasNumber": "",
                "balance": 996,
                "imageFileName": "http://172.24.1.56:7002/ETPStoreServiceV5.5/ProductImageDownloadServlet?imagename=ACKIDBELTJEBURTON-1-00001.jpg",
                "itemDescription": "Black Medium",
                "itemName": "Kids MMT Belt Black Medium",
                "itemNumber": "ACKIDBELTJEBURTON-1-00001",
                "location": "APP01",
                "productGroup": "BELTS",
                "salesPrice": 4
            },
            {
                "HSNCode": "1",
                "UOM": "PCS",
                "aliasNumber": "",
                "balance": 987,
                "imageFileName": "http://172.24.1.56:7002/ETPStoreServiceV5.5/ProductImageDownloadServlet?imagename=ACKIDBELTJEBURTON-1-00002.jpg",
                "itemDescription": "MAGENTA Small",
                "itemName": "Kids MMT Belt MAGENTA Small",
                "itemNumber": "ACKIDBELTJEBURTON-1-00002",
                "location": "APP01",
                "productGroup": "BELTS",
                "salesPrice": 4
            },
            {
                "HSNCode": "61012000",
                "UOM": "PCS",
                "aliasNumber": "",
                "balance": 999,
                "imageFileName": "http://172.24.1.56:7002/ETPStoreServiceV5.5/ProductImageDownloadServlet?imagename=ACKIDBELTJEBURTON-1-00003.jpg",
                "itemDescription": "MAGENTA Xtra Large",
                "itemName": "Kids MMT Belt MAGENTA Xtra Lar",
                "itemNumber": "ACKIDBELTJEBURTON-1-00003",
                "location": "APP01",
                "productGroup": "BELTS",
                "salesPrice": 4
            },
            {
                "HSNCode": "61012000",
                "UOM": "PCS",
                "aliasNumber": "",
                "balance": 999,
                "imageFileName": "http://172.24.1.56:7002/ETPStoreServiceV5.5/ProductImageDownloadServlet?imagename=ACKIDBELTJEBURTON-1-00004.jpg",
                "itemDescription": "Black Small",
                "itemName": "Kids MMT Belt Black Small",
                "itemNumber": "ACKIDBELTJEBURTON-1-00004",
                "location": "APP01",
                "productGroup": "BELTS",
                "salesPrice": 4
            }
        ],
        "productInputInfo": {
            "aliasNumber": "",
            "inputParameter": "",
            "itemDescription": "",
            "itemGroup": "",
            "itemName": "",
            "itemNumber": ""
        },
        "requestInfo": {
            "requestKey": "UNpMbqpWd0wIdNuNBugWmVlUnMNvwTPobwvZcXFXZZ2WXiIdWKSRsnGVTpi0dsAB"
        }
    }
]